README.rst
setup.py
applause/__init__.py
applause/__main__.py
applause/ais.py
applause/auth.py
applause/beta.py
applause/buaps.py
applause/compat.py
applause/errors.py
applause/param.py
applause/product.py
applause/sdk.py
applause/session.py
applause/settings.py
applause/utils.py
applause/tests/__init__.py
applause/tests/test_ais.py
applause/tests/test_auth.py
applause/tests/test_beta.py
applause/tests/test_buaps.py
applause/tests/test_sdk.py
applause/tests/test_session.py
applause/tests/test_utils.py
applause_tool.egg-info/PKG-INFO
applause_tool.egg-info/SOURCES.txt
applause_tool.egg-info/dependency_links.txt
applause_tool.egg-info/entry_points.txt
applause_tool.egg-info/not-zip-safe
applause_tool.egg-info/requires.txt
applause_tool.egg-info/top_level.txt