Metadata-Version: 1.1
Name: applause-tool
Version: 0.5.0
Summary: This package allows integration with Applause Inc. services.
Home-page: UNKNOWN
Author: Applause Team
Author-email: eng.warsaw@applause.com
License: MIT
Platform: UNKNOWN
Classifier: Programming Language :: Python :: 2.6
Classifier: Programming Language :: Python :: 2.7
Classifier: Programming Language :: Python :: 3.4
Classifier: Topic :: Utilities
Classifier: Topic :: System :: Shells
Classifier: Topic :: System :: Software Distribution
Classifier: Topic :: Software Development :: Quality Assurance
Classifier: Topic :: Software Development :: Testing
